ssb_jordbruk_fagfunksjoner/__init__.py
ssb_jordbruk_fagfunksjoner/__main__.py
ssb_jordbruk_fagfunksjoner/produksjonstilskudd.py
ssb_jordbruk_fagfunksjoner/py.typed
ssb_jordbruk_fagfunksjoner-0.3.0.dist-info/LICENSE
ssb_jordbruk_fagfunksjoner-0.3.0.dist-info/METADATA
ssb_jordbruk_fagfunksjoner-0.3.0.dist-info/WHEEL
ssb_jordbruk_fagfunksjoner-0.3.0.dist-info/entry_points.txt
ssb_jordbruk_fagfunksjoner-0.3.0.dist-info/RECORD
