Metadata-Version: 2.3
Name: ssb-jordbruk-fagfunksjoner
Version: 0.3.0
Summary: SSB Jordbruk Fagfunksjoner
License: MIT
Author: Magnus Theodor Engh
Author-email: dor@ssb.no
Requires-Python: >=3.10,<4.0
Classifier: Development Status :: 3 - Alpha
Classifier: License :: OSI Approved :: MIT License
Classifier: Programming Language :: Python :: 3
Classifier: Programming Language :: Python :: 3.10
Classifier: Programming Language :: Python :: 3.11
Classifier: Programming Language :: Python :: 3.12
Classifier: Programming Language :: Python :: 3.13
Requires-Dist: click (>=8.0.1)
Requires-Dist: typeguard (>=4.4.1,<5.0.0)
Project-URL: Changelog, https://github.com/statisticsnorway/ssb-jordbruk-fagfunksjoner/releases
Project-URL: Documentation, https://statisticsnorway.github.io/ssb-jordbruk-fagfunksjoner
Project-URL: Homepage, https://github.com/statisticsnorway/ssb-jordbruk-fagfunksjoner
Project-URL: Repository, https://github.com/statisticsnorway/ssb-jordbruk-fagfunksjoner
